Metadata-Version: 2.4
Name: tencent-wedata3-auto-ml
Version: 0.1.1
Summary: AutoML SDK for Tencent Cloud WeData using FLAML with MLflow integration.
Home-page: https://git.woa.com/WeDataOS/wedata-automl
Author: ZhangChunLin
Author-email: blueszzhang@tencent.com
License: MIT
Project-URL: Homepage, https://git.woa.com/WeDataOS/wedata-automl
Project-URL: Repository, https://git.woa.com/WeDataOS/wedata-automl.git
Classifier: Programming Language :: Python :: 3
Classifier: Programming Language :: Python :: 3.9
Classifier: Programming Language :: Python :: 3.10
Classifier: Programming Language :: Python :: 3.11
Classifier: License :: OSI Approved :: MIT License
Classifier: Operating System :: OS Independent
Requires-Python: >=3.9
Requires-Dist: flaml==2.3.6
Requires-Dist: lightgbm>=4.0.0
Requires-Dist: xgboost>=2.0.0
Requires-Dist: prophet>=1.1
Requires-Dist: statsmodels>=0.13
Requires-Dist: holidays>=0.25
Requires-Dist: catboost>=1.0.0
Requires-Dist: scikit-learn<1.7,>=1.5
Requires-Dist: numpy<3.0,>=1.24
Requires-Dist: matplotlib>=3.5
Requires-Dist: seaborn>=0.11
Provides-Extra: xgboost
Requires-Dist: xgboost>=1.6; extra == "xgboost"
Provides-Extra: lightgbm
Requires-Dist: lightgbm>=3.3; extra == "lightgbm"
Provides-Extra: wedata
Requires-Dist: tencent-wedata-feature-engineering; extra == "wedata"
Provides-Extra: shap
Requires-Dist: shap>=0.41; extra == "shap"
Provides-Extra: full
Requires-Dist: xgboost>=1.6; extra == "full"
Requires-Dist: lightgbm>=3.3; extra == "full"
Requires-Dist: tencent-wedata-feature-engineering>=0.1.36; extra == "full"
Requires-Dist: shap>=0.41; extra == "full"
Requires-Dist: optuna==4.6.0; extra == "full"
Requires-Dist: flaml[spark]==2.3.6; extra == "full"
Requires-Dist: cachetools>=5.0.0; extra == "full"
Requires-Dist: tencentcloud-sdk-python-common>=3.0.1478; extra == "full"
Dynamic: author
Dynamic: author-email
Dynamic: classifier
Dynamic: description
Dynamic: description-content-type
Dynamic: home-page
Dynamic: license
Dynamic: project-url
Dynamic: provides-extra
Dynamic: requires-dist
Dynamic: requires-python
Dynamic: summary
